{
  "meta": {
    "title": "周易生命史（2.0兼容投影）",
    "subtitle": "由生命史知识模型2.0自动导出",
    "span": {
      "start": -700,
      "end": 1989
    },
    "sourceSchema": "2.0.0",
    "note": "此文件保持旧版 eras/versions/works/scholars 结构，供视觉迁移测试使用。"
  },
  "eras": [
    {
      "name": "先秦",
      "start": -700,
      "end": -206
    },
    {
      "name": "汉",
      "start": -206,
      "end": 220
    },
    {
      "name": "魏晋南北朝",
      "start": 220,
      "end": 589
    },
    {
      "name": "隋唐",
      "start": 589,
      "end": 907
    },
    {
      "name": "宋元",
      "start": 960,
      "end": 1368
    },
    {
      "name": "明清",
      "start": 1368,
      "end": 1911
    },
    {
      "name": "现代",
      "start": 1912,
      "end": 1989
    }
  ],
  "versions": [
    {
      "id": "classic",
      "name": "今本文本系统",
      "short": "今本",
      "start": -700,
      "end": 1989,
      "description": "传世《周易》经传及其历代注释共同依托的主干文本系统。围绕经传、传世本等核心议题，这一系统汇聚《易传》等代表节点，显示文本传承、解释方法与学术共同体之间的连续关系。《周易研究史》在“绪论”的论述中将其作为观察该阶段文本解释、方法选择与学术传承如何互动的重要节点。",
      "v2Id": "system:received"
    },
    {
      "id": "preqin-divination",
      "name": "先秦占筮易说",
      "short": "占筮",
      "start": -700,
      "end": -221,
      "description": "以具体筮例、卦象和吉凶判断为中心的早期易说。它围绕占筮、象数等核心议题展开，是理解相关文本传承、解释方法和学术分化的重要历史坐标。《周易研究史》在“第一章·先秦时期的各家易说”的论述中将其作为观察该阶段文本解释、方法选择与学术传承如何互动的重要节点。",
      "v2Id": "school:preqin-divination"
    },
    {
      "id": "preqin-yili",
      "name": "先秦义理易说",
      "short": "先秦义理",
      "start": -600,
      "end": -221,
      "description": "由卦爻辞阐发德行、政治与人事义理的先秦解释传统。围绕义理、儒家等核心议题，这一系统汇聚孔子等代表节点，显示文本传承、解释方法与学术共同体之间的连续关系。《周易研究史》在“第一章·先秦时期的各家易说”的论述中将其作为观察该阶段文本解释、方法选择与学术传承如何互动的重要节点。",
      "v2Id": "school:preqin-yili"
    },
    {
      "id": "silk",
      "name": "帛书《周易》",
      "short": "帛书",
      "start": -168,
      "end": 1989,
      "description": "马王堆帛书保存的《周易》经传异本，为早期文本形态研究提供新的材料。围绕出土文献、异本等核心议题，这一系统汇聚李学勤帛书《易传》研究等代表节点，显示文本传承、解释方法与学术共同体之间的连续关系。《周易研究史》在“第七章·现代考据易学”的论述中将其作为观察该阶段文本解释、方法选择与学术传承如何互动的重要节点。",
      "v2Id": "system:silk"
    },
    {
      "id": "hanxiang",
      "name": "汉代象数易",
      "short": "汉代象数",
      "start": -100,
      "end": 260,
      "description": "以卦气、八宫、纳甲、爻辰等方法解易的两汉象数传统。围绕象数、卦气、纳甲等核心议题，这一系统汇聚京氏易学、《易纬》、郑玄《周易注》等代表节点，显示文本传承、解释方法与学术共同体之间的连续关系。《周易研究史》在“第二章·两汉象数易学的崛起”的论述中将其作为观察该阶段文本解释、方法选择与学术传承如何互动的重要节点。",
      "v2Id": "school:han-xiangshu"
    },
    {
      "id": "huanglao",
      "name": "两汉黄老与道教易",
      "short": "黄老道教易",
      "start": -100,
      "end": 300,
      "description": "以黄老思想、拟经著作和炼养理论吸收易学资源的传统。围绕黄老、道教、应用易学等核心议题，这一系统汇聚《太玄》、《周易参同契》等代表节点，显示文本传承、解释方法与学术共同体之间的连续关系。《周易研究史》在“第二章·两汉黄老派易学”的论述中将其作为观察该阶段文本解释、方法选择与学术传承如何互动的重要节点。",
      "v2Id": "school:huanglao"
    },
    {
      "id": "feishi",
      "name": "费氏古文易",
      "short": "费氏易",
      "start": -50,
      "end": 220,
      "description": "以古文经传授和经传相附为特征，并深刻影响东汉易学的传统。围绕古文经、经传等核心议题，这一系统汇聚费直、马融等代表节点，显示文本传承、解释方法与学术共同体之间的连续关系。《周易研究史》在“第二章·费氏古文易的兴盛”的论述中将其作为观察该阶段文本解释、方法选择与学术传承如何互动的重要节点。",
      "v2Id": "school:feishi"
    },
    {
      "id": "wangbi",
      "name": "王弼本系统",
      "short": "王弼本",
      "start": 240,
      "end": 1080,
      "description": "以王弼《周易注》和韩康伯传注为核心的玄学义理解释系统。围绕玄学、义理等核心议题，这一系统汇聚王弼《周易注》、韩康伯等代表节点，显示文本传承、解释方法与学术共同体之间的连续关系。《周易研究史》在“第三章·玄学义理派”的论述中将其作为观察该阶段文本解释、方法选择与学术传承如何互动的重要节点。",
      "v2Id": "system:wangbi"
    },
    {
      "id": "zhengyi",
      "name": "《周易正义》系统",
      "short": "正义",
      "start": 653,
      "end": 1500,
      "description": "唐代官修义疏对王韩注本的整理与权威化所形成的经学系统。围绕义疏、官学等核心议题，这一系统汇聚孔颖达《周易正义》等代表节点，显示文本传承、解释方法与学术共同体之间的连续关系。《周易研究史》在“第三章·孔颖达和《周易正义》”的论述中将其作为观察该阶段文本解释、方法选择与学术传承如何互动的重要节点。",
      "v2Id": "system:zhengyi"
    },
    {
      "id": "jijie",
      "name": "《周易集解》系统",
      "short": "集解",
      "start": 735,
      "end": 1360,
      "description": "李鼎祚汇集汉魏易注而形成的保存象数易材料的重要文本系统。围绕集注、辑佚、象数等核心议题，这一系统汇聚李鼎祚《周易集解》等代表节点，显示文本传承、解释方法与学术共同体之间的连续关系。《周易研究史》在“第三章·李鼎祚及其《周易集解》”的论述中将其作为观察该阶段文本解释、方法选择与学术传承如何互动的重要节点。",
      "v2Id": "system:jijie"
    },
    {
      "id": "song-tushu",
      "name": "宋代图书象数易",
      "short": "图书易",
      "start": 960,
      "end": 1300,
      "description": "围绕河图、洛书、先天图和数理推演展开的宋代象数传统。围绕河图洛书、先天图、象数等核心议题，这一系统汇聚《太极图说》、《皇极经世》、《汉上易传》等代表节点，显示文本传承、解释方法与学术共同体之间的连续关系。《周易研究史》在“第四章·北宋象数派易学”的论述中将其作为观察该阶段文本解释、方法选择与学术传承如何互动的重要节点。",
      "v2Id": "school:song-tushu"
    },
    {
      "id": "cheng",
      "name": "程氏易学",
      "short": "程氏",
      "start": 1093,
      "end": 1600,
      "description": "以程颐及其《伊川易传》为核心、重视人事义理和经世解释的研究传统；它是学者共同体，不属于经典文本核心。围绕义理、理学等核心议题，这一系统汇聚《伊川易传》、《横渠易说》、《周易内传》《周易外传》等代表节点，显示文本传承、解释方法与学术共同体之间的连续关系。",
      "v2Id": "system:cheng"
    },
    {
      "id": "zhu",
      "name": "朱子易学",
      "short": "朱子",
      "start": 1187,
      "end": 1905,
      "description": "以朱熹及其《周易本义》为核心、兼取义理、象数与占筮并长期影响经学教育的研究传统；它作为学派环绕经典文本核心。围绕理学、卜筮、义理等核心议题，这一系统汇聚朱熹《周易本义》、《易学启蒙》等代表节点，显示文本传承、解释方法与学术共同体之间的连续关系。",
      "v2Id": "system:zhu"
    },
    {
      "id": "qing",
      "name": "清代考据易学",
      "short": "考据易",
      "start": 1650,
      "end": 1905,
      "description": "通过校勘、辑佚和汉易复原展开的清代朴学易传统。围绕朴学、考据、汉易等核心议题，这一系统汇聚《易图明辨》、惠栋《周易述》、张惠言《周易虞氏义》等代表节点，显示文本传承、解释方法与学术共同体之间的连续关系。《周易研究史》在“第六章·朴学易的发展”的论述中将其作为观察该阶段文本解释、方法选择与学术传承如何互动的重要节点。",
      "v2Id": "school:qing-kaoju"
    },
    {
      "id": "modern-critical",
      "name": "现代考据与新方法易学",
      "short": "现代易学",
      "start": 1910,
      "end": 1989,
      "description": "以疑古、考古、哲学史和现代学术方法重新研究《周易》的多元传统。围绕疑古、考古、现代学术等核心议题，这一系统汇聚高亨《周易古经今注》、李镜池《周易探源》、《周易古义》等代表节点，显示文本传承、解释方法与学术共同体之间的连续关系。",
      "v2Id": "school:modern-critical"
    }
  ],
  "works": [
    {
      "id": "yizhuan",
      "name": "《易传》",
      "short": "易传",
      "start": -350,
      "end": 180,
      "description": "围绕《周易》经文形成的传释文献群，是后世易学义理和象数解释的重要基础。该著作围绕十翼、经传等问题，由相关注家和研究者持续阐发，可在今本文本系统的演变脉络中理解其历史位置。《周易研究史》在“第一章·由传而经的《易传》”的论述中将其作为观察该阶段文本解释、方法选择与学术传承如何互动的重要节点。",
      "v2Id": "work:yizhuan",
      "parent": "classic"
    },
    {
      "id": "yiwei",
      "name": "《易纬》",
      "short": "易纬",
      "start": -100,
      "end": 200,
      "description": "以象数、卦气和谶纬观念解释《易》的文献群。该著作围绕纬书、卦气等问题，由相关注家和研究者持续阐发，可在汉代象数易的演变脉络中理解其历史位置。《周易研究史》在“第二章·《易纬》与象数学”的论述中将其作为观察该阶段文本解释、方法选择与学术传承如何互动的重要节点。",
      "v2Id": "work:yiwei",
      "parent": "hanxiang"
    },
    {
      "id": "jingshi",
      "name": "京氏易学",
      "short": "京氏易学",
      "start": -50,
      "end": 220,
      "description": "京房及其传承所形成的卦气、八宫、纳甲等象数方法体系。该著作围绕卦气、八宫、纳甲等问题，由京房的研究展开，可在汉代象数易的演变脉络中理解其历史位置。《周易研究史》在“第二章·京房易学”的论述中将其作为观察该阶段文本解释、方法选择与学术传承如何互动的重要节点。",
      "v2Id": "work:jingfang-corpus",
      "parent": "hanxiang"
    },
    {
      "id": "taixuan",
      "name": "《太玄》",
      "short": "太玄",
      "start": -10,
      "end": 10,
      "description": "扬雄拟《易》而作的宇宙论和符号体系著作。该著作围绕黄老、拟经等问题，由扬雄的研究展开，可在两汉黄老与道教易的演变脉络中理解其历史位置。《周易研究史》在“第二章·扬雄与《太玄》”的论述中将其作为观察该阶段文本解释、方法选择与学术传承如何互动的重要节点。",
      "v2Id": "work:taixuan",
      "parent": "huanglao"
    },
    {
      "id": "cantongqi",
      "name": "《周易参同契》",
      "short": "周易参同契",
      "start": 120,
      "end": 220,
      "description": "将易学象数与炼养思想结合的重要道教易学著作。该著作围绕月体纳甲、炼丹、道教等问题，由魏伯阳的研究展开，可在两汉黄老与道教易的演变脉络中理解其历史位置。《周易研究史》在“第二章·魏伯阳与《周易参同契》”的论述中将其作为观察该阶段文本解释、方法选择与学术传承如何互动的重要节点。",
      "v2Id": "work:cantongqi",
      "parent": "huanglao"
    },
    {
      "id": "zhengxuan-work",
      "name": "郑玄《周易注》",
      "short": "郑玄周易注",
      "start": 180,
      "end": 200,
      "description": "郑玄融会礼学、爻辰与象数方法形成的《周易》注本。该著作围绕爻辰、礼学、象数等问题，由郑玄的研究展开，可在汉代象数易的演变脉络中理解其历史位置。《周易研究史》在“第二章·郑玄的五行生成说与爻辰说”的论述中将其作为观察该阶段文本解释、方法选择与学术传承如何互动的重要节点。",
      "v2Id": "work:zhengxuan-zhouyizhu",
      "parent": "hanxiang"
    },
    {
      "id": "wangbi-work",
      "name": "王弼《周易注》",
      "short": "王弼周易注",
      "start": 240,
      "end": 249,
      "description": "以简约玄理重释卦爻、推动玄学义理易兴起的注本。该著作围绕玄学、得意忘象等问题，由王弼的研究展开，可在王弼本系统的演变脉络中理解其历史位置。《周易研究史》在“第三章·王弼易学”的论述中将其作为观察该阶段文本解释、方法选择与学术传承如何互动的重要节点。",
      "v2Id": "work:wangbi-zhouyizhu",
      "parent": "wangbi"
    },
    {
      "id": "zhengyi-work",
      "name": "孔颖达《周易正义》",
      "short": "孔颖达周易正义",
      "start": 640,
      "end": 653,
      "description": "唐代官修五经正义之一，以王韩注为本汇释前说。该著作围绕义疏、官学等问题，由孔颖达的研究展开，可在《周易正义》系统的演变脉络中理解其历史位置。《周易研究史》在“第三章·孔颖达和《周易正义》”的论述中将其作为观察该阶段文本解释、方法选择与学术传承如何互动的重要节点。",
      "v2Id": "work:zhouyi-zhengyi",
      "parent": "zhengyi"
    },
    {
      "id": "jijie-work",
      "name": "李鼎祚《周易集解》",
      "short": "李鼎祚周易集解",
      "start": 700,
      "end": 780,
      "description": "汇集汉魏多家易注、保存大量象数易佚说的唐代集注。该著作围绕集注、汉易、辑佚等问题，由李鼎祚的研究展开，可在《周易集解》系统的演变脉络中理解其历史位置。《周易研究史》在“第三章·李鼎祚及其《周易集解》”的论述中将其作为观察该阶段文本解释、方法选择与学术传承如何互动的重要节点。",
      "v2Id": "work:zhouyi-jijie",
      "parent": "jijie"
    },
    {
      "id": "huangji-jingshi",
      "name": "《皇极经世》",
      "short": "皇极经世",
      "start": 1050,
      "end": 1077,
      "description": "邵雍以先天象数和数理结构推演天地历史的代表作。该著作围绕先天易、数理、历史哲学等问题，由邵雍的研究展开，可在宋代图书象数易的演变脉络中理解其历史位置。《周易研究史》在“第四章·邵雍的易学”的论述中将其作为观察该阶段文本解释、方法选择与学术传承如何互动的重要节点。",
      "v2Id": "work:huangji-jingshi",
      "parent": "song-tushu"
    },
    {
      "id": "hengqu-yishuo",
      "name": "《横渠易说》",
      "short": "横渠易说",
      "start": 1060,
      "end": 1077,
      "description": "张载以气论和义理解释《周易》的著作。该著作围绕气学、义理等问题，由张载的研究展开，可在程氏易学的演变脉络中理解其历史位置。《周易研究史》在“第五章·张载的易学”的论述中将其作为观察该阶段文本解释、方法选择与学术传承如何互动的重要节点。",
      "v2Id": "work:hengqu-yishuo",
      "parent": "cheng"
    },
    {
      "id": "taijitu-shuo",
      "name": "《太极图说》",
      "short": "太极图说",
      "start": 1060,
      "end": 1073,
      "description": "周敦颐借太极图式阐述宇宙生成与人伦修养的短篇著作。该著作围绕太极、理学等问题，由周敦颐的研究展开，可在宋代图书象数易的演变脉络中理解其历史位置。《周易研究史》在“第四章·周敦颐的易学”的论述中将其作为观察该阶段文本解释、方法选择与学术传承如何互动的重要节点。",
      "v2Id": "work:taijitu-shuo",
      "parent": "song-tushu"
    },
    {
      "id": "cheng-work",
      "name": "《伊川易传》",
      "short": "伊川易传",
      "start": 1093,
      "end": 1107,
      "description": "程颐以人事义理和理学立场解释《周易》的代表作。该著作围绕义理、理学等问题，由程颐的研究展开，可在程氏易学的演变脉络中理解其历史位置。《周易研究史》在“第五章·程颐的易学”的论述中将其作为观察该阶段文本解释、方法选择与学术传承如何互动的重要节点。",
      "v2Id": "work:yichuan-yizhuan",
      "parent": "cheng"
    },
    {
      "id": "hanshang-yizhuan",
      "name": "《汉上易传》",
      "short": "汉上易传",
      "start": 1120,
      "end": 1138,
      "description": "朱震会通汉易象数与宋代图书学的代表性易著。该著作围绕汉易、图书易等问题，由朱震的研究展开，可在宋代图书象数易的演变脉络中理解其历史位置。《周易研究史》在“第四章·朱震的易学”的论述中将其作为观察该阶段文本解释、方法选择与学术传承如何互动的重要节点。",
      "v2Id": "work:hanshang-yizhuan",
      "parent": "song-tushu"
    },
    {
      "id": "zhu-work",
      "name": "朱熹《周易本义》",
      "short": "朱熹周易本义",
      "start": 1180,
      "end": 1187,
      "description": "朱熹重申《易》为卜筮之书并会通义理、象数的代表性注本。该著作围绕本义、卜筮、理学等问题，由朱熹的研究展开，可在朱子易学的演变脉络中理解其历史位置。《周易研究史》在“第五章·朱熹的易学”的论述中将其作为观察该阶段文本解释、方法选择与学术传承如何互动的重要节点。",
      "v2Id": "work:zhouyi-benyi",
      "parent": "zhu"
    },
    {
      "id": "wangfuzhi-work",
      "name": "《周易内传》《周易外传》",
      "short": "周易内传周易外传",
      "start": 1650,
      "end": 1692,
      "description": "王夫之以气论和历史哲学阐发易理的两部相关著作。该著作围绕气论、义理等问题，由王夫之的研究展开，可在程氏易学的演变脉络中理解其历史位置。《周易研究史》在“第六章·明末清初义理派宋易”的论述中将其作为观察该阶段文本解释、方法选择与学术传承如何互动的重要节点。",
      "v2Id": "work:zhouyi-neizhuan-waizhuan",
      "parent": "cheng"
    },
    {
      "id": "yitu-mingbian",
      "name": "《易图明辨》",
      "short": "易图明辨",
      "start": 1700,
      "end": 1706,
      "description": "胡渭系统辨析河图、洛书与宋代易图源流的考据著作。该著作围绕辨伪、图书学、考据等问题，由胡渭的研究展开，可在清代考据易学的演变脉络中理解其历史位置。《周易研究史》在“第六章·胡渭的《易图明辨》”的论述中将其作为观察该阶段文本解释、方法选择与学术传承如何互动的重要节点。",
      "v2Id": "work:yitu-mingbian",
      "parent": "qing"
    },
    {
      "id": "huidong-work",
      "name": "惠栋《周易述》",
      "short": "惠栋周易述",
      "start": 1740,
      "end": 1758,
      "description": "惠栋辑释汉代易说、重建汉易传统的重要著作。该著作围绕汉易、考据、辑佚等问题，由惠栋的研究展开，可在清代考据易学的演变脉络中理解其历史位置。《周易研究史》在“第六章·惠栋对汉易的研究”的论述中将其作为观察该阶段文本解释、方法选择与学术传承如何互动的重要节点。",
      "v2Id": "work:zhouyi-shu",
      "parent": "qing"
    },
    {
      "id": "jiaoxun-work",
      "name": "焦循易学三书",
      "short": "焦循易学三书",
      "start": 1790,
      "end": 1820,
      "description": "焦循运用数学与语言分析重构易学关系的《易通释》《易图略》《易章句》。该著作围绕数学、语言学、象数等问题，由焦循的研究展开，可在清代考据易学的演变脉络中理解其历史位置。《周易研究史》在“第六章·焦循对象数易学的创新”的论述中将其作为观察该阶段文本解释、方法选择与学术传承如何互动的重要节点。",
      "v2Id": "work:jiaoxun-yixue",
      "parent": "qing"
    },
    {
      "id": "zhy-work",
      "name": "张惠言《周易虞氏义》",
      "short": "张惠言周易虞氏义",
      "start": 1790,
      "end": 1802,
      "description": "以虞翻易学为中心整理和阐发汉易的清代著作。该著作围绕虞氏易、汉易、考据等问题，由张惠言的研究展开，可在清代考据易学的演变脉络中理解其历史位置。《周易研究史》在“第六章·张惠言对《虞氏易》的研究”的论述中将其作为观察该阶段文本解释、方法选择与学术传承如何互动的重要节点。",
      "v2Id": "work:zhouyi-yushi-yi",
      "parent": "qing"
    },
    {
      "id": "gaoheng-work",
      "name": "高亨《周易古经今注》",
      "short": "高亨周易古经今注",
      "start": 1930,
      "end": 1950,
      "description": "以现代考据方法解释《周易》古经的代表性著作。该著作围绕现代考据、古史辨等问题，由高亨的研究展开，可在现代考据与新方法易学的演变脉络中理解其历史位置。《周易研究史》在“第七章·现代易学”的论述中将其作为观察该阶段文本解释、方法选择与学术传承如何互动的重要节点。",
      "v2Id": "work:zhouyi-gujing-jinzhu",
      "parent": "modern-critical"
    },
    {
      "id": "lijingchi-work",
      "name": "李镜池《周易探源》",
      "short": "李镜池周易探源",
      "start": 1930,
      "end": 1940,
      "description": "从古史辨和文献考据角度讨论《周易》性质与成书问题的著作。该著作围绕疑古、成书研究等问题，由李镜池的研究展开，可在现代考据与新方法易学的演变脉络中理解其历史位置。《周易研究史》在“第七章·现代易学”的论述中将其作为观察该阶段文本解释、方法选择与学术传承如何互动的重要节点。",
      "v2Id": "work:zhouyi-tanyuan",
      "parent": "modern-critical"
    }
  ],
  "scholars": [
    {
      "id": "kongzi",
      "name": "孔子",
      "short": "孔子",
      "start": -551,
      "end": -479,
      "description": "先秦义理解易传统的重要代表，后世《易传》作者问题亦长期围绕其展开。从书中所述的学术位置来看，其核心问题涉及先秦、义理，并与先秦义理易说构成可追踪的传承、发展或论辩关系。《周易研究史》在“绪论·易学历史分期”的论述中将其作为观察该阶段文本解释、方法选择与学术传承如何互动的重要节点。",
      "v2Id": "person:kongzi",
      "parent": "preqin-yili"
    },
    {
      "id": "mengxi",
      "name": "孟喜",
      "short": "孟喜",
      "start": -100,
      "end": -40,
      "description": "西汉象数易学代表，以卦气说著称。从书中所述的学术位置来看，其核心问题涉及卦气、象数，并与汉代象数易、京房构成可追踪的传承、发展或论辩关系。《周易研究史》在“第二章·孟喜的卦气说”的论述中将其作为观察该阶段文本解释、方法选择与学术传承如何互动的重要节点。",
      "v2Id": "person:mengxi",
      "parent": "hanxiang"
    },
    {
      "id": "jingfang",
      "name": "京房",
      "short": "京房",
      "start": -77,
      "end": -37,
      "description": "西汉易学家，发展卦气，并以八宫、纳甲等方法形成京氏易学。从其代表著述京氏易学来看，核心问题涉及卦气、八宫、纳甲，并与京氏易学、孟喜构成可追踪的传承、发展或论辩关系。《周易研究史》在“第二章·京房易学”的论述中将其作为观察该阶段文本解释、方法选择与学术传承如何互动的重要节点。",
      "v2Id": "person:jingfang",
      "parent": "jingshi"
    },
    {
      "id": "feizhi",
      "name": "费直",
      "short": "费直",
      "start": -60,
      "end": 10,
      "description": "西汉古文易传承的重要人物，费氏易对东汉易学影响显著。从书中所述的学术位置来看，其核心问题涉及古文经、费氏易，并与费氏古文易构成可追踪的传承、发展或论辩关系。《周易研究史》在“第二章·费氏古文易”的论述中将其作为观察该阶段文本解释、方法选择与学术传承如何互动的重要节点。",
      "v2Id": "person:feizhi",
      "parent": "feishi"
    },
    {
      "id": "yangxiong",
      "name": "扬雄",
      "short": "扬雄",
      "start": -53,
      "end": 18,
      "description": "汉代思想家，以《太玄》拟《易》构建新的符号和思想体系。从其代表著述《太玄》来看，核心问题涉及太玄、黄老，并与《太玄》构成可追踪的传承、发展或论辩关系。《周易研究史》在“第二章·扬雄与《太玄》”的论述中将其作为观察该阶段文本解释、方法选择与学术传承如何互动的重要节点。",
      "v2Id": "person:yangxiong",
      "parent": "taixuan"
    },
    {
      "id": "marong",
      "name": "马融",
      "short": "马融",
      "start": 79,
      "end": 166,
      "description": "东汉经学家，其易学传承连接费氏古文易与郑玄。从书中所述的学术位置来看，其核心问题涉及古文经、经学，并与费氏古文易、郑玄构成可追踪的传承、发展或论辩关系。《周易研究史》在“第二章·东汉古文易”的论述中将其作为观察该阶段文本解释、方法选择与学术传承如何互动的重要节点。",
      "v2Id": "person:marong",
      "parent": "feishi"
    },
    {
      "id": "weiboyang",
      "name": "魏伯阳",
      "short": "魏伯阳",
      "start": 100,
      "end": 200,
      "description": "传统上被视为《周易参同契》的重要作者或代表人物。从其代表著述《周易参同契》来看，核心问题涉及参同契、道教，并与《周易参同契》构成可追踪的传承、发展或论辩关系。《周易研究史》在“第二章·魏伯阳与《周易参同契》”的论述中将其作为观察该阶段文本解释、方法选择与学术传承如何互动的重要节点。",
      "v2Id": "person:weiboyang",
      "parent": "cantongqi"
    },
    {
      "id": "zhengxuan",
      "name": "郑玄",
      "short": "郑玄",
      "start": 127,
      "end": 200,
      "description": "东汉经学家，以礼学、五行生成和爻辰等方法注易。从其代表著述郑玄《周易注》来看，核心问题涉及爻辰、礼学、象数，并与郑玄《周易注》、马融构成可追踪的传承、发展或论辩关系。《周易研究史》在“第二章·郑玄的五行生成说与爻辰说”的论述中将其作为观察该阶段文本解释、方法选择与学术传承如何互动的重要节点。",
      "v2Id": "person:zhengxuan",
      "parent": "zhengxuan-work"
    },
    {
      "id": "xunshuang",
      "name": "荀爽",
      "short": "荀爽",
      "start": 128,
      "end": 190,
      "description": "东汉象数易学家，以阳升阴降等说解释卦爻变化。从书中所述的学术位置来看，其核心问题涉及升降、象数，并与汉代象数易、虞翻构成可追踪的传承、发展或论辩关系。《周易研究史》在“第二章·荀爽与阳升阴降说”的论述中将其作为观察该阶段文本解释、方法选择与学术传承如何互动的重要节点。",
      "v2Id": "person:xunshuang",
      "parent": "hanxiang"
    },
    {
      "id": "yufan",
      "name": "虞翻",
      "short": "虞翻",
      "start": 164,
      "end": 233,
      "description": "汉末三国易学家，综合卦变、旁通、互体等象数方法。从书中所述的学术位置来看，其核心问题涉及卦变、旁通、互体，并与汉代象数易、荀爽、朱震构成可追踪的传承、发展或论辩关系。《周易研究史》在“第二章·虞翻对象数学的贡献”的论述中将其作为观察该阶段文本解释、方法选择与学术传承如何互动的重要节点。",
      "v2Id": "person:yufan",
      "parent": "hanxiang"
    },
    {
      "id": "wangbi-s",
      "name": "王弼",
      "short": "王弼",
      "start": 226,
      "end": 249,
      "description": "魏晋玄学义理易的关键人物，以简约义理重释《周易》。从其代表著述王弼《周易注》来看，核心问题涉及玄学、义理、得意忘象，并与王弼《周易注》构成可追踪的传承、发展或论辩关系。《周易研究史》在“第三章·王弼易学”的论述中将其作为观察该阶段文本解释、方法选择与学术传承如何互动的重要节点。",
      "v2Id": "person:wangbi",
      "parent": "wangbi-work"
    },
    {
      "id": "hankangbo",
      "name": "韩康伯",
      "short": "韩康伯",
      "start": 332,
      "end": 380,
      "description": "东晋易学家，承续王弼玄学义理传统并注释《系辞》等传。从书中所述的学术位置来看，其核心问题涉及玄学、义理，并与王弼本系统构成可追踪的传承、发展或论辩关系。《周易研究史》在“第三章·韩康伯对王弼易学的发展”的论述中将其作为观察该阶段文本解释、方法选择与学术传承如何互动的重要节点。",
      "v2Id": "person:hankangbo",
      "parent": "wangbi"
    },
    {
      "id": "kongyingda",
      "name": "孔颖达",
      "short": "孔颖达",
      "start": 574,
      "end": 648,
      "description": "唐代经学家，主持《周易正义》编纂并确立王韩注本的官学地位。从其代表著述孔颖达《周易正义》来看，核心问题涉及义疏、官学，并与孔颖达《周易正义》构成可追踪的传承、发展或论辩关系。《周易研究史》在“第三章·孔颖达和《周易正义》”的论述中将其作为观察该阶段文本解释、方法选择与学术传承如何互动的重要节点。",
      "v2Id": "person:kongyingda",
      "parent": "zhengyi-work"
    },
    {
      "id": "lidingzuo",
      "name": "李鼎祚",
      "short": "李鼎祚",
      "start": 700,
      "end": 780,
      "description": "唐代易学家，编纂《周易集解》保存汉魏多家易注。从其代表著述李鼎祚《周易集解》来看，核心问题涉及集注、汉易，并与李鼎祚《周易集解》构成可追踪的传承、发展或论辩关系。《周易研究史》在“第三章·李鼎祚及其《周易集解》”的论述中将其作为观察该阶段文本解释、方法选择与学术传承如何互动的重要节点。",
      "v2Id": "person:lidingzuo",
      "parent": "jijie-work"
    },
    {
      "id": "chentuan",
      "name": "陈抟",
      "short": "陈抟",
      "start": 871,
      "end": 989,
      "description": "宋代图书易学源流中的关键人物，后世多种先天图说与其相联系。从书中所述的学术位置来看，其核心问题涉及图书易、先天图，并与宋代图书象数易、刘牧、李之才构成可追踪的传承、发展或论辩关系。《周易研究史》在“第四章·北宋图书易学”的论述中将其作为观察该阶段文本解释、方法选择与学术传承如何互动的重要节点。",
      "v2Id": "person:chentuan",
      "parent": "song-tushu"
    },
    {
      "id": "liumu",
      "name": "刘牧",
      "short": "刘牧",
      "start": 1011,
      "end": 1064,
      "description": "北宋象数易学家，以河图洛书和数理图式解释《易》。从其代表著述《易数钩隐图》来看，核心问题涉及河图洛书、象数，并与《易数钩隐图》、宋代图书象数易、陈抟构成可追踪的传承、发展或论辩关系。《周易研究史》在“第四章·陈抟、刘牧、李之才的易学”的论述中将其作为观察该阶段文本解释、方法选择与学术传承如何互动的重要节点。",
      "v2Id": "person:liumu",
      "parent": "song-tushu"
    },
    {
      "id": "shaoyong",
      "name": "邵雍",
      "short": "邵雍",
      "start": 1011,
      "end": 1077,
      "description": "北宋象数学家，以先天图式与数理系统建立皇极经世之学。从其代表著述《皇极经世》来看，核心问题涉及先天易、象数、数理，并与《皇极经世》、宋代图书象数易、李之才构成可追踪的传承、发展或论辩关系。《周易研究史》在“第四章·邵雍的易学”的论述中将其作为观察该阶段文本解释、方法选择与学术传承如何互动的重要节点。",
      "v2Id": "person:shaoyong",
      "parent": "huangji-jingshi"
    },
    {
      "id": "zhoudunyi",
      "name": "周敦颐",
      "short": "周敦颐",
      "start": 1017,
      "end": 1073,
      "description": "北宋思想家，以《太极图说》连接宇宙生成论与理学修养论。从其代表著述《太极图说》来看，核心问题涉及太极、理学，并与《太极图说》构成可追踪的传承、发展或论辩关系。《周易研究史》在“第四章·周敦颐的易学”的论述中将其作为观察该阶段文本解释、方法选择与学术传承如何互动的重要节点。",
      "v2Id": "person:zhoudunyi",
      "parent": "taijitu-shuo"
    },
    {
      "id": "zhangzai",
      "name": "张载",
      "short": "张载",
      "start": 1020,
      "end": 1077,
      "description": "北宋思想家，以气论构造具有自身特色的义理易学。从其代表著述《横渠易说》来看，核心问题涉及气学、义理，并与《横渠易说》、杨万里构成可追踪的传承、发展或论辩关系。《周易研究史》在“第五章·张载的易学”的论述中将其作为观察该阶段文本解释、方法选择与学术传承如何互动的重要节点。",
      "v2Id": "person:zhangzai",
      "parent": "hengqu-yishuo"
    },
    {
      "id": "chengyi",
      "name": "程颐",
      "short": "程颐",
      "start": 1033,
      "end": 1107,
      "description": "北宋理学家，以人事义理和守理观解释《周易》。从其代表著述《伊川易传》来看，核心问题涉及理学、义理，并与《伊川易传》、朱熹构成可追踪的传承、发展或论辩关系。《周易研究史》在“第五章·程颐的易学”的论述中将其作为观察该阶段文本解释、方法选择与学术传承如何互动的重要节点。",
      "v2Id": "person:chengyi",
      "parent": "cheng-work"
    },
    {
      "id": "zhuzhen",
      "name": "朱震",
      "short": "朱震",
      "start": 1072,
      "end": 1138,
      "description": "南宋易学家，会通汉易象数与宋代图书学。从其代表著述《汉上易传》来看，核心问题涉及汉易、图书易，并与《汉上易传》、虞翻构成可追踪的传承、发展或论辩关系。《周易研究史》在“第四章·朱震的易学”的论述中将其作为观察该阶段文本解释、方法选择与学术传承如何互动的重要节点。",
      "v2Id": "person:zhuzhen",
      "parent": "hanshang-yizhuan"
    },
    {
      "id": "zhuxi",
      "name": "朱熹",
      "short": "朱熹",
      "start": 1130,
      "end": 1200,
      "description": "南宋理学家，以《周易本义》综合义理、象数与卜筮问题。从其代表著述朱熹《周易本义》、《易学启蒙》来看，核心问题涉及理学、本义、卜筮，并与朱熹《周易本义》、《易学启蒙》、程颐构成可追踪的传承、发展或论辩关系。《周易研究史》在“第五章·朱熹的易学”的论述中将其作为观察该阶段文本解释、方法选择与学术传承如何互动的重要节点。",
      "v2Id": "person:zhuxi",
      "parent": "zhu-work"
    },
    {
      "id": "huangzongxi",
      "name": "黄宗羲",
      "short": "黄宗羲",
      "start": 1610,
      "end": 1695,
      "description": "清初思想家，批判宋代图书象数并考辨易图源流。从书中所述的学术位置来看，其核心问题涉及图书辨伪、义理，并与清代考据易学、宋代图书象数易、清初图书辨伪构成可追踪的传承、发展或论辩关系。《周易研究史》在“第六章·黄宗羲、黄宗炎对图书象数学的批判”的论述中将其作为观察该阶段文本解释、方法选择与学术传承如何互动的重要节点。",
      "v2Id": "person:huangzongxi",
      "parent": "qing"
    },
    {
      "id": "guyanwu",
      "name": "顾炎武",
      "short": "顾炎武",
      "start": 1613,
      "end": 1682,
      "description": "清初学者，其音韵与考据工作被视为清代朴学易的先声。从书中所述的学术位置来看，其核心问题涉及考据、经世，并与清代考据易学构成可追踪的传承、发展或论辩关系。《周易研究史》在“第六章·顾炎武的易学思想”的论述中将其作为观察该阶段文本解释、方法选择与学术传承如何互动的重要节点。",
      "v2Id": "person:guyanwu",
      "parent": "qing"
    },
    {
      "id": "wangfuzhi",
      "name": "王夫之",
      "short": "王夫之",
      "start": 1619,
      "end": 1692,
      "description": "明清之际思想家，以气论、历史观和义理重新阐释《周易》。从其代表著述《周易内传》《周易外传》来看，核心问题涉及气论、义理，并与《周易内传》《周易外传》构成可追踪的传承、发展或论辩关系。《周易研究史》在“第六章·明末清初义理派宋易”的论述中将其作为观察该阶段文本解释、方法选择与学术传承如何互动的重要节点。",
      "v2Id": "person:wangfuzhi",
      "parent": "wangfuzhi-work"
    },
    {
      "id": "huwei",
      "name": "胡渭",
      "short": "胡渭",
      "start": 1633,
      "end": 1714,
      "description": "清初考据学家，以《易图明辨》系统辨析宋代易图。从其代表著述《易图明辨》来看，核心问题涉及图书辨伪、考据，并与《易图明辨》、宋代图书象数易、清初图书辨伪构成可追踪的传承、发展或论辩关系。《周易研究史》在“第六章·胡渭的《易图明辨》”的论述中将其作为观察该阶段文本解释、方法选择与学术传承如何互动的重要节点。",
      "v2Id": "person:huwei",
      "parent": "yitu-mingbian"
    },
    {
      "id": "huidong",
      "name": "惠栋",
      "short": "惠栋",
      "start": 1697,
      "end": 1758,
      "description": "清代汉学家，辑录和重建汉易文献传统。从其代表著述惠栋《周易述》来看，核心问题涉及汉易、考据，并与惠栋《周易述》、汉代象数易构成可追踪的传承、发展或论辩关系。《周易研究史》在“第六章·惠栋对汉易的研究”的论述中将其作为观察该阶段文本解释、方法选择与学术传承如何互动的重要节点。",
      "v2Id": "person:huidong",
      "parent": "huidong-work"
    },
    {
      "id": "zhanghuiyan",
      "name": "张惠言",
      "short": "张惠言",
      "start": 1761,
      "end": 1802,
      "description": "清代学者，以虞翻易学为中心整理和发展汉易。从其代表著述张惠言《周易虞氏义》来看，核心问题涉及虞氏易、考据，并与张惠言《周易虞氏义》、虞翻构成可追踪的传承、发展或论辩关系。《周易研究史》在“第六章·张惠言对《虞氏易》的研究”的论述中将其作为观察该阶段文本解释、方法选择与学术传承如何互动的重要节点。",
      "v2Id": "person:zhanghuiyan",
      "parent": "zhy-work"
    },
    {
      "id": "jiaoxun",
      "name": "焦循",
      "short": "焦循",
      "start": 1763,
      "end": 1820,
      "description": "清代学者，运用数学和语言分析创新象数易研究。从其代表著述焦循易学三书来看，核心问题涉及数学、语言学、象数，并与焦循易学三书构成可追踪的传承、发展或论辩关系。《周易研究史》在“第六章·焦循对象数易学的创新”的论述中将其作为观察该阶段文本解释、方法选择与学术传承如何互动的重要节点。",
      "v2Id": "person:jiaoxun",
      "parent": "jiaoxun-work"
    },
    {
      "id": "gujiegang",
      "name": "顾颉刚",
      "short": "顾颉刚",
      "start": 1893,
      "end": 1980,
      "description": "现代古史辨派代表，以历史考辨重新讨论卦爻辞故事和成书问题。从书中所述的学术位置来看，其核心问题涉及古史辨、疑古，并与现代考据与新方法易学、屈万里、严灵峰构成可追踪的传承、发展或论辩关系。《周易研究史》在“第七章·现代易学”的论述中将其作为观察该阶段文本解释、方法选择与学术传承如何互动的重要节点。",
      "v2Id": "person:gujiegang",
      "parent": "modern-critical"
    },
    {
      "id": "gaoheng",
      "name": "高亨",
      "short": "高亨",
      "start": 1900,
      "end": 1986,
      "description": "现代易学家，以古文字、训诂和文献考据研究《周易》经传。从其代表著述高亨《周易古经今注》来看，核心问题涉及考据、训诂，并与高亨《周易古经今注》、现代考据与新方法易学构成可追踪的传承、发展或论辩关系。《周易研究史》在“第七章·现代易学”的论述中将其作为观察该阶段文本解释、方法选择与学术传承如何互动的重要节点。",
      "v2Id": "person:gaoheng",
      "parent": "gaoheng-work"
    },
    {
      "id": "lijingchi",
      "name": "李镜池",
      "short": "李镜池",
      "start": 1902,
      "end": 1975,
      "description": "现代易学家，以古史辨方法讨论《周易》性质、编纂和经传年代。从其代表著述李镜池《周易探源》来看，核心问题涉及古史辨、成书研究，并与李镜池《周易探源》、屈万里、魏莱构成可追踪的传承、发展或论辩关系。《周易研究史》在“第七章·现代易学”的论述中将其作为观察该阶段文本解释、方法选择与学术传承如何互动的重要节点。",
      "v2Id": "person:lijingchi",
      "parent": "lijingchi-work"
    }
  ]
}
